aleph/__init__.py
aleph/core/ALEPH.py
aleph/core/Bioinformatics.py
aleph/core/Grid.py
aleph/core/SystemUtility.py
aleph/core/__init__.py
aleph/core/managerSSH.py
aleph/gui/alephui.py
aleph/gui/annotation.py
aleph/gui/backend.py
aleph/gui/decomposition.py
aleph/gui/download_pdb.py
aleph/gui/library.py
aleph/gui/settings.py
aleph/gui/superposition.py
aleph/gui/ui_aleph.py
aleph/gui/ui_annotation.py
aleph/gui/ui_decomposition.py
aleph/gui/ui_library.py
aleph/gui/ui_settings.py
aleph/gui/ui_superposition.py
aleph/gui/dist/ngl.html
aleph/gui/dist/ngl.js
aleph/gui/img/annotation.png
aleph/gui/img/cursor_v-split_arrow-512.png
aleph/gui/img/decomposition.png
aleph/gui/img/icon.png
aleph/gui/img/library.png
aleph/gui/img/oldicon.png
aleph/gui/img/screenshot.png
aleph/gui/img/splitter.png
aleph/gui/img/splitter_h.png
aleph/gui/img/superposition.png
aleph-1.4.2.dist-info/LICENSE
aleph-1.4.2.dist-info/METADATA
aleph-1.4.2.dist-info/WHEEL
aleph-1.4.2.dist-info/entry_points.txt
aleph-1.4.2.dist-info/top_level.txt
aleph-1.4.2.dist-info/RECORD
