Metadata-Version: 2.1
Name: aleph
Version: 1.4.2
Summary: ALEPH is a bioinformatics tool for structure interpretation and generation of fragment-based library for Molecular Replacement.
Home-page: http://chango.ibmb.csic.es/ALEPH
Author: Massimo Domenico Sammito
Author-email: alephbugs@gmail.com
Keywords: crystallography macromolecular bioinformatics networks
Classifier: Operating System :: Unix
Classifier: Development Status :: 5 - Production/Stable
Classifier: Intended Audience :: Science/Research 
Classifier: Topic :: Scientific/Engineering :: Bio-Informatics
Classifier: License :: OSI Approved :: BSD License
Classifier: Programming Language :: Python :: 3 :: Only
License-File: LICENSE
Requires-Dist: biopython
Requires-Dist: matplotlib
Requires-Dist: paramiko
Requires-Dist: numpy
Requires-Dist: scipy
Requires-Dist: pandas
Requires-Dist: cython
Requires-Dist: python-igraph
Requires-Dist: psutil
Requires-Dist: scikit-learn
Requires-Dist: termcolor
Requires-Dist: wget
Requires-Dist: future
Requires-Dist: pyside2
Requires-Dist: pyopengl
Requires-Dist: shiboken2
